pandasai/__init__.py
pandasai/constants.py
pandasai/dfagent/__init__.py
pandasai/dfagent/base.py
pandasai/dfagent/prompt.py
pandasai/dfagent/result.py
pandasai/exceptions.py
pandasai/helpers/__init__.py
pandasai/helpers/_optional.py
pandasai/helpers/anonymizer.py
pandasai/helpers/cache.py
pandasai/helpers/from_excel.py
pandasai/helpers/notebook.py
pandasai/helpers/save_chart.py
pandasai/helpers/shortcuts.py
pandasai/langchain/__init__.py
pandasai/langchain/agents.py
pandasai/llm/__init__.py
pandasai/llm/azure_openai.py
pandasai/llm/base.py
pandasai/llm/fake.py
pandasai/llm/falcon.py
pandasai/llm/google_palm.py
pandasai/llm/langchain.py
pandasai/llm/model.py
pandasai/llm/open_assistant.py
pandasai/llm/openai.py
pandasai/llm/starcoder.py
pandasai/middlewares/__init__.py
pandasai/middlewares/base.py
pandasai/middlewares/charts.py
pandasai/middlewares/streamlit.py
pandasai/prompts/__init__.py
pandasai/prompts/base.py
pandasai/prompts/correct_error_prompt.py
pandasai/prompts/correct_multiples_prompt.py
pandasai/prompts/generate_python_code.py
pandasai/prompts/generate_response.py
pandasai/prompts/multiple_dataframes.py
idoctorai-0.8.7.dist-info/entry_points.txt
idoctorai-0.8.7.dist-info/LICENSE
idoctorai-0.8.7.dist-info/METADATA
idoctorai-0.8.7.dist-info/WHEEL
idoctorai-0.8.7.dist-info/RECORD
