Metadata-Version: 2.1
Name: idoctorai
Version: 0.8.7
Summary: Idoctor AI is a Python library that integrates generative artificial intelligence capabilities into Pandas.
License: MIT
Author: FH
Requires-Python: >=3.9, !=2.7.*, !=3.0.*, !=3.1.*, !=3.2.*, !=3.3.*, !=3.4.*, !=3.5.*, !=3.6.*, !=3.7.*, !=3.8.*
Classifier: License :: OSI Approved :: MIT License
Classifier: Programming Language :: Python :: 3
Classifier: Programming Language :: Python :: 3.9
Classifier: Programming Language :: Python :: 3.10
Classifier: Programming Language :: Python :: 3.11
Provides-Extra: google
Provides-Extra: google-cloud
Provides-Extra: tests
Requires-Dist: astor (>=0.8.1,<0.9.0)
Requires-Dist: ggplot (>=0.11.5,<0.12.0)
Requires-Dist: google-cloud-aiplatform (>=1.26.1,<2.0.0) ; extra == "google-cloud"
Requires-Dist: google-generativeai (>=0.1.0rc2,<0.2.0) ; extra == "google"
Requires-Dist: ipython (>=8.13.1,<9.0.0)
Requires-Dist: langchain (>=0.0.299,<0.0.300)
Requires-Dist: matplotlib (>=3.7.1,<4.0.0)
Requires-Dist: numpy (>=1.17,<2.0) ; extra == "tests"
Requires-Dist: openai (>=0.27.5,<0.28.0)
Requires-Dist: pandas (==1.5.3)
Requires-Dist: plotly (>=5.14.1,<6.0.0)
Requires-Dist: python-dotenv (>=1.0.0,<2.0.0)
Requires-Dist: scikit-learn (>=1.2.2,<2.0.0)
Requires-Dist: seaborn (>=0.12.2,<0.13.0) ; extra == "tests"
Requires-Dist: statsmodels (>=0.14.0,<0.15.0)
Requires-Dist: streamlit (>=1.23.1,<2.0.0)
Requires-Dist: tabulate (>=0.9.0,<0.10.0)
